ecoe/__init__.py
ecoe/econ/__init__.py
ecoe/econ/econ.py
ecoe/geo/__init__.py
ecoe/geo/geo.py
ecoe/hydro/__init__.py
ecoe/hydro/hydro.py
ecoe/modeling/__init__.py
ecoe-0.0.15.dist-info/LICENSE
ecoe-0.0.15.dist-info/METADATA
ecoe-0.0.15.dist-info/WHEEL
ecoe-0.0.15.dist-info/top_level.txt
ecoe-0.0.15.dist-info/RECORD
