Metadata-Version: 2.1
Name: ecoe
Version: 0.0.15
Summary: Package for Ecological Engineering Applications
Home-page: https://github.com/OSU-BEE/ecoe
Author: John Bolte
Author-email: john.bolte@oregonstate.edu
License: UNKNOWN
Keywords: ecological engineering python
Platform: UNKNOWN
Classifier: License :: OSI Approved :: GNU General Public License (GPL)
Classifier: Operating System :: OS Independent
Classifier: Development Status :: 3 - Alpha
Classifier: Programming Language :: Python :: 3.5
Classifier: Programming Language :: Python :: 3.6
Classifier: Programming Language :: Python :: 3.7
Classifier: Programming Language :: Python :: 3.8
Requires-Python: >=3.5
Requires-Dist: numpy
Requires-Dist: pandas
Requires-Dist: matplotlib
